geojsonfix/__init__.py
geojsonfix/checks_invalid.py
geojsonfix/checks_problematic.py
geojsonfix/fix_invalid.py
geojsonfix/fix_problematic.py
geojsonfix/fixes_invalid.py
geojsonfix/fixes_problematic.py
geojsonfix/geometry_utils.py
geojsonfix/main.py
geojsonfix-0.0.2.data/data/requirements.txt
geojsonfix-0.0.2.dist-info/METADATA
geojsonfix-0.0.2.dist-info/WHEEL
geojsonfix-0.0.2.dist-info/top_level.txt
geojsonfix-0.0.2.dist-info/RECORD
