Metadata-Version: 2.1
Name: geojsonfix
Version: 0.0.2
Summary: Validates and fixes GeoJSON
Home-page: https://github.com/chrieke/geojsonfix
Author: Christoph Rieke
Author-email: christoph.k.rieke@gmail.com
License: MIT
Classifier: Programming Language :: Python :: 3
Classifier: License :: OSI Approved :: MIT License
Classifier: Operating System :: OS Independent
Classifier: Development Status :: 4 - Beta
Classifier: Intended Audience :: Developers
Requires-Python: >=3.8
Requires-Dist: shapely
Requires-Dist: loguru
